elasticroute/__init__.py
elasticroute/clients.py
elasticroute/common.py
elasticroute/dashboard.py
elasticroute/deserializers.py
elasticroute/repositories.py
elasticroute/routing.py
elasticroute/serializers.py
elasticroute/validators.py
elasticroute/errors/__init__.py
elasticroute/errors/repository.py
elasticroute/errors/validator.py
elasticroute/warnings/__init__.py
elasticroute/warnings/bean.py
elasticroute-2.0.2.dist-info/LICENSE
elasticroute-2.0.2.dist-info/METADATA
elasticroute-2.0.2.dist-info/WHEEL
elasticroute-2.0.2.dist-info/top_level.txt
elasticroute-2.0.2.dist-info/RECORD
