Metadata-Version: 2.1
Name: elasticroute
Version: 2.0.2
Summary: Free, intelligent routing for your logistics – now on Python
Home-page: https://github.com/detrack/elasticroute-python
Author: Detrack
Author-email: chester@detack.com
License: UNKNOWN
Platform: UNKNOWN
Classifier: Programming Language :: Python :: 3
Classifier: License :: OSI Approved :: MIT License
Classifier: Operating System :: OS Independent
Requires-Dist: requests
